rocket/__init__.py
rocket/rocket.py
rocket_0_8_7-0.8.7.dist-info/LICENSE.txt
rocket_0_8_7-0.8.7.dist-info/METADATA
rocket_0_8_7-0.8.7.dist-info/WHEEL
rocket_0_8_7-0.8.7.dist-info/top_level.txt
rocket_0_8_7-0.8.7.dist-info/RECORD
