Metadata-Version: 2.1
Name: rocket_0_8_7
Version: 0.8.7
Summary: A package for simulating rockets and space shuttles.
Home-page: https://github.com/amaliahm/rocket
Author: aminaghandouz
Author-email: a.ghandouz@esi-sba.dz
Classifier: Programming Language :: Python :: 3
Classifier: License :: OSI Approved :: MIT License
Classifier: Operating System :: OS Independent
Requires-Python: >=3.6
License-File: LICENSE.txt
